vpc_sh.py
vpc.sh-0.1.dist-info/entry_points.txt
vpc.sh-0.1.dist-info/metadata.json
vpc.sh-0.1.dist-info/DESCRIPTION.rst
vpc.sh-0.1.dist-info/top_level.txt
vpc.sh-0.1.dist-info/METADATA
vpc.sh-0.1.dist-info/WHEEL
vpc.sh-0.1.dist-info/RECORD
