Metadata-Version: 2.0
Name: vpc.sh
Version: 0.1
Summary: CLI tool to run shell commands on ec2 instances.
Home-page: https://github.com/achirko/vpc.sh
Author: Oleksandr Chyrko
Author-email: aleksandr.chirko@gmail.com
License: UNKNOWN
Platform: UNKNOWN
Classifier: Environment :: Console
Classifier: Intended Audience :: Developers
Classifier: Intended Audience :: System Administrators
Classifier: License :: OSI Approved :: BSD License
Classifier: Operating System :: Unix
Classifier: Operating System :: POSIX
Classifier: Programming Language :: Python
Classifier: Programming Language :: Python :: 2.7
Classifier: Topic :: System :: Clustering
Classifier: Topic :: System :: Systems Administration
Requires-Dist: Click
Requires-Dist: boto
Requires-Dist: fabric
Requires-Dist: tabulate
